pvrecorder/LICENSE
pvrecorder/__init__.py
pvrecorder/_pvrecorder.py
pvrecorder/lib/linux/x86_64/libpv_recorder.so
pvrecorder/lib/mac/arm64/libpv_recorder.dylib
pvrecorder/lib/mac/x86_64/libpv_recorder.dylib
pvrecorder/lib/raspberry-pi/arm11/libpv_recorder.so
pvrecorder/lib/raspberry-pi/cortex-a53/libpv_recorder.so
pvrecorder/lib/raspberry-pi/cortex-a53-aarch64/libpv_recorder.so
pvrecorder/lib/raspberry-pi/cortex-a72/libpv_recorder.so
pvrecorder/lib/raspberry-pi/cortex-a72-aarch64/libpv_recorder.so
pvrecorder/lib/raspberry-pi/cortex-a76/libpv_recorder.so
pvrecorder/lib/raspberry-pi/cortex-a76-aarch64/libpv_recorder.so
pvrecorder/lib/windows/amd64/libpv_recorder.dll
pvrecorder/lib/windows/arm64/libpv_recorder.dll
pvrecorder-1.2.6.dist-info/METADATA
pvrecorder-1.2.6.dist-info/WHEEL
pvrecorder-1.2.6.dist-info/top_level.txt
pvrecorder-1.2.6.dist-info/RECORD
